jupytercad/__init__.py
jupytercad_lite-3.4.0.dist-info/METADATA
jupytercad_lite-3.4.0.dist-info/WHEEL
jupytercad_lite-3.4.0.dist-info/licenses/LICENSE
jupytercad_lite-3.4.0.dist-info/RECORD
